Metadata-Version: 2.1
Name: unames
Version: 1.0.3
Summary: Generate username from the full name provided
Home-page: https://github.com/chankruze/unames
Author: chankruze
Author-email: chankruze@gmail.com
License: UNKNOWN
Platform: UNKNOWN
Classifier: License :: OSI Approved :: GNU General Public License v3 or later (GPLv3+)
Classifier: Operating System :: OS Independent
Classifier: Programming Language :: Python
Classifier: Programming Language :: Python :: 3
Classifier: Programming Language :: Python :: 3.9
License-File: LICENSE
